LICENSE.txt
README.md
setup.py
iSFun.egg-info/PKG-INFO
iSFun.egg-info/SOURCES.txt
iSFun.egg-info/dependency_links.txt
iSFun.egg-info/requires.txt
iSFun.egg-info/top_level.txt
isfun/Iscca.py
isfun/Iscca_cv.py
isfun/Iscca_plot.py
isfun/Ispca.py
isfun/Ispca_cv.py
isfun/Ispca_plot.py
isfun/Ispls.py
isfun/Ispls_cv.py
isfun/Ispls_plot.py
isfun/Meta_scca.py
isfun/Meta_spca.py
isfun/Meta_spls.py
isfun/Preview_cca.py
isfun/Preview_pca.py
isfun/Preview_pls.py
isfun/Scca.py
isfun/Spca.py
isfun/Spls.py
isfun/__init__.py
isfun_data/__init__.py
isfun_data/cca_dict.pkl
isfun_data/pca_dict.pkl
isfun_data/pls_dict.pkl
isfun_data/simData_cca.py
isfun_data/simData_pca.py
isfun_data/simData_pls.py